[

    {

        "id": "1a2b3c4d5e6f",

        "type": "tab",

        "label": "Demo Flow",

        "disabled": false,

        "info": ""

    },

    {

        "id": "e61385b54fdde383",

        "type": "inject",

        "z": "1a2b3c4d5e6f",

        "name": "",

        "props": [

            {

                "p": "payload"

            },

            {

                "p": "topic",

                "vt": "str"

            }

        ],

        "repeat": "",

        "crontab": "",

        "once": false,

        "onceDelay": 0.1,

        "topic": "",

        "payload": "",

        "payloadType": "date",

        "x": 100,

        "y": 240,

        "wires": [

            [

                "c12d212bb621842a"

            ]

        ]

    },

    {

        "id": "c12d212bb621842a",

        "type": "delay",

        "z": "1a2b3c4d5e6f",

        "name": "",

        "pauseType": "delay",

        "timeout": "3",

        "timeoutUnits": "seconds",

        "rate": "1",

        "nbRateUnits": "1",

        "rateUnits": "second",

        "randomFirst": "1",

        "randomLast": "5",

        "randomUnits": "seconds",

        "drop": false,

        "allowrate": false,

        "outputs": 1,

        "x": 320,

        "y": 240,

        "wires": [

            [

                "a67e9dacfef54ec5"

            ]

        ]

    },

    {

        "id": "a67e9dacfef54ec5",

        "type": "debug",

        "z": "1a2b3c4d5e6f",

        "name": "debug 1",

        "active": true,

        "tosidebar": true,

        "console": false,

        "tostatus": false,

        "complete": "false",

        "statusVal": "",

        "statusType": "auto",

        "x": 510,

        "y": 240,

        "wires": []

    }

]